{
  "VPCSubnetRange" : {
    "Description" : "The IP range to use for the VPC.",
    "Type" : "String",
    "MinLength" : "9",
    "MaxLength" : "18",
    "Default" : "10.0.0.0/16",
    "AllowedPattern" : "^([0-9]+\\.){3}[0-9]+\\/[0-9]+$",
    "ConstraintDescription" : "must be a valid CIDR."
  },
  "PrivateSubnetRange" : {
    "Description" : "The IP range to use for the private subnet.",
    "Type" : "String",
    "MinLength" : "9",
    "MaxLength" : "18",
    "Default" : "10.0.0.0/22",
    "AllowedPattern" : "^([0-9]+\\.){3}[0-9]+\\/[0-9]+$",
    "ConstraintDescription" : "must be a valid CIDR."
  },
  "PublicSubnetRange" : {
    "Description" : "The IP range to use for the public subnet.",
    "Type" : "String",
    "MinLength" : "9",
    "MaxLength" : "18",
    "Default" : "10.0.4.0/22",
    "AllowedPattern" : "^([0-9]+\\.){3}[0-9]+\\/[0-9]+$",
    "ConstraintDescription" : "must be a valid CIDR."
  },
  "FallbackDNS" : {
    "Description" : "The IP to use for fallback DNS (base of VPC network range plus two).",
    "Type" : "String",
    "MinLength" : "7",
    "MaxLength" : "13",
    "Default" : "10.0.0.2",
    "AllowedPattern" : "^([0-9]+\\.){3}2",
    "ConstraintDescription" : "must be a valid IP with last octet 2."
  },
  "MasterInstanceType" : {
    "Description" : "EC2 instance type",
    "Type" : "String",
    "Default" : "m3.xlarge",
    "AllowedValues" : [ "t1.micro","t2.micro","t2.small","t2.medium","m1.small","m1.medium","m1.large","m1.xlarge","m2.xlarge","m2.2xlarge","m2.4xlarge","m3.medium","m3.large","m3.xlarge","m3.2xlarge","c1.medium","c1.xlarge","cc1.4xlarge","cc2.8xlarge","cg1.4xlarge","r3.large","r3.xlarge","r3.2xlarge","r3.4xlarge","r3.8xlarge"],
    "ConstraintDescription" : "must be a valid EC2 instance type."
  },
  "SlaveInstanceType" : {
    "Description" : "EC2 instance type",
    "Type" : "String",
    "Default" : "m3.xlarge",
    "AllowedValues" : [ "t1.micro","t2.micro","t2.small","t2.medium","m1.small","m1.medium","m1.large","m1.xlarge","m2.xlarge","m2.2xlarge","m2.4xlarge","m3.medium","m3.large","m3.xlarge","m3.2xlarge","c1.medium","c1.xlarge","cc1.4xlarge","cc2.8xlarge","cg1.4xlarge","r3.large","r3.xlarge","r3.2xlarge","r3.4xlarge","r3.8xlarge"],
    "ConstraintDescription" : "must be a valid EC2 instance type."
  },
  "PublicSlaveInstanceType" : {
    "Description" : "EC2 instance type",
    "Type" : "String",
    "Default" : "m3.xlarge",
    "AllowedValues" : [ "t1.micro","t2.micro","t2.small","t2.medium","m1.small","m1.medium","m1.large","m1.xlarge","m2.xlarge","m2.2xlarge","m2.4xlarge","m3.medium","m3.large","m3.xlarge","m3.2xlarge","c1.medium","c1.xlarge","cc1.4xlarge","cc2.8xlarge","cg1.4xlarge","r3.large","r3.xlarge","r3.2xlarge","r3.4xlarge","r3.8xlarge"],
    "ConstraintDescription" : "must be a valid EC2 instance type."
  },
  "MasterInstanceCount" : {
    "Description" : "Number of master nodes to launch",
    "Type" : "Number",
    "Default" : "1"
  },
  "MasterQuorumCount" : {
    "Description" : "Number of masters needed for Mesos replicated log registry quorum (should be ceiling(<MasterInstanceCount>/2))",
    "Type" : "Number",
    "Default" : "1"
  },
  "BootstrapRepoRoot" : {
    "Description" : "Root repository for bootstrapping (must not end in /)",
    "Type" : "String",
    "Default" : ""
  },
  "StackCreationTimeout" : {
    "Description" : "Timeout on initial stack creation",
    "Type" : "String",
    "Default": "PT30M"
  }
}
